[
  {
    "title": "BFA graduate exhibition",
    "year": "2019",
    "venue": "Shenkar College, Department of Multidisciplinary Art",
    "description": " \"Solo group exhibition\", BFA graduate exhibition at the Department of \nMultidisciplinary Art, Shenkar. ",
    "images": []
  },
  {
    "title": "Ritual",
    "year": "2026",
    "venue": "Solo exhivition at Jerusalem Artists' House — curated by Hadas Glazer",
    "description": "21 Feb — 30 May, 2026\nIn Elad Amsalem’s solo exhibition, Ritual, symbols, actions, and events transform the space into a liminal zone between the mundane, the ceremonial, and the artistic, inviting a reconsideration of one’s relationship with art, and of the values of beauty and illusion. Amsalem challenges boundaries, inquiring where the work of art takes place.\nThe exhibition consists of a series of repeated actions within a meaning-laden painterly space, enabling a transition from the everyday to other states of consciousness. It transpires on three levels: the act of painting as repeated application and erasure; the ritual spaces inhabited by the figures, which are set apart from routine life; and the exhibition space, where the encounter with the audience may produce a shift and suggest a fresh way of seeing. The distinction between these levels draws the viewer back to the primary ritual—the act of painting.\nAmsalem’s ritual practice is rooted in primitivism and de-skilling: drawing away from the figure of the artist as a virtuoso master, and replacing the ideal of “good work” with simple, unraveled, symbolic gestures. Painting does not aspire to technical quality, perspective, or illusion, but to a moment of freedom that emerges within the ritual of painting.\nWhen consciousness strips itself of the “correct” principles of painting, another type of beauty reveals itself. Amsalem likens such painting to flamenco: an intuitive entanglement of gestures, which gives rise to a simple, precise solution. The moment of grace is the moment of disentangling, without perfection and without a consensual ideal of beauty.\nThe paintings carry a sense of the outdoors and of open space, alongside a rawness that emphasizes painting as a material object, rather than a mere image. The ceramics and frayed edges function like “grounding wires,” expanding the painting and linking the two-dimensional with the three-dimensional, and the depicted world with the viewing space. Along the axis between figurative and abstract, the question arises: what is “primitive” here—the freedom from the image, or rather the figures themselves? Perhaps their function is to bind the corporeal world to the painting. Rather than creating a seductive illusion, the painting exposes its underlying seams. Thus, the shift proposed by the exhibition takes us back to the starting point, to the act of painting itself as a ritual; not a mechanism of control and perfection, but a space in which unraveling, inquiry, and reinvention of the seemingly self-evident become possible.\n\nHadas Glazer\n\t\n\n",
    "images": [
      "/media/works/jah-005-1780915457989.jpg",
      "/media/works/jah-006-1780915473909.jpg",
      "/media/works/jah-007-1780915483464.jpg",
      "/media/works/jah-008-1780915493251.jpg",
      "/media/works/jah-009-1780915500705.jpg",
      "/media/works/jah-010-1780915508773.jpg"
    ]
  },
  {
    "title": "Nature of Man",
    "year": "2022",
    "venue": " Solo exhibition at Nulobaz Gallery",
    "description": "A solo exhibition presenting the figure within nature — between the real and the visionary.",
    "images": [
      "/media/works/img-1375-1780917530942.jpg",
      "/media/works/img-1373-1780917541456.jpg",
      "/media/works/img-1376-1780917546722.jpg",
      "/media/works/d33e82cf-d360-4766-bb4e-6854c7758fe6-1780917555137.jpg",
      "/media/works/362c4b70-67e2-48c1-a3eb-fe69060d172a-1780917560187.jpg",
      "/media/works/1670f7f4-5624-4021-8881-d656129280a1-1780917574396.jpg"
    ]
  }
]
